<?xml version="1.0" encoding="UTF-8"?>
<LanguageData>
  <!-- EN: AK-101 -->
  <Gun_AK-101_RWP.label>AK-101</Gun_AK-101_RWP.label>
  <!-- EN: . -->
  <Gun_AK-101_RWP.description>.</Gun_AK-101_RWP.description>
  <!-- EN: stock -->
  <Gun_AK-101_RWP.tools.stock.label>stock</Gun_AK-101_RWP.tools.stock.label>
  <!-- EN: barrel -->
  <Gun_AK-101_RWP.tools.barrel.label>barrel</Gun_AK-101_RWP.tools.barrel.label>
  <!-- EN: AK-101 -->
  <Gun_AK-101_RWP.verbs.Verb_Shoot.label>AK-101</Gun_AK-101_RWP.verbs.Verb_Shoot.label>
</LanguageData>
